solid/__init__.py
solid/octo_functions.py
solid_always_wins-0.1.dist-info/DESCRIPTION.rst
solid_always_wins-0.1.dist-info/METADATA
solid_always_wins-0.1.dist-info/RECORD
solid_always_wins-0.1.dist-info/WHEEL
solid_always_wins-0.1.dist-info/metadata.json
solid_always_wins-0.1.dist-info/top_level.txt
