Metadata-Version: 2.0
Name: solid-always-wins
Version: 0.1
Summary: The most solid joke in the world
Home-page: https://github.com/ageorgou/solid-octo-succotash
Author: A. and T.
Author-email: flyingcircus@example.com
License: MIT
Platform: UNKNOWN
